phoopy/__init__.py
phoopy/kernel/__init__.py
phoopy/kernel/bundle.py
phoopy/kernel/container.py
phoopy/kernel/kernel.py
phoopy_kernel-1.2.0.dist-info/LICENSE.md
phoopy_kernel-1.2.0.dist-info/METADATA
phoopy_kernel-1.2.0.dist-info/WHEEL
phoopy_kernel-1.2.0.dist-info/top_level.txt
phoopy_kernel-1.2.0.dist-info/RECORD
